{
  "name": "Loot | Nalfeshnee",
  "img": "icons/containers/bags/pack-simple-leather.webp",
  "description": "true",
  "results": [
    {
      "type": 0,
      "weight": 1,
      "range": [
        1,
        20
      ],
      "drawn": false,
      "documentCollection": "",
      "text": "[[/r 4d6*100]]{Silver}[[/r 1d6*100]]{Gold}",
      "img": "icons/commodities/currency/coins-assorted-mix-copper.webp",
      "documentId": null,
      "flags": {},
      "_id": "2CUEGZ0H11Yk6GsV",
      "_key": "!tables.results!5SkqTTSbeGviEehL.2CUEGZ0H11Yk6GsV"
    },
    {
      "type": 0,
      "weight": 1,
      "range": [
        21,
        35
      ],
      "drawn": false,
      "documentCollection": "",
      "text": "[[/r 1d6*100]]{Electrum}[[/r 1d6*100]]{Gold}",
      "img": "icons/commodities/currency/coins-assorted-mix-copper.webp",
      "documentId": null,
      "flags": {},
      "_id": "KZd2uflUlMxHe327",
      "_key": "!tables.results!5SkqTTSbeGviEehL.KZd2uflUlMxHe327"
    },
    {
      "type": 0,
      "weight": 1,
      "range": [
        36,
        75
      ],
      "drawn": false,
      "documentCollection": "",
      "text": "[[/r 2d6*100]]{Gold}[[/r 1d6*10]]{Platinum}",
      "img": "icons/commodities/currency/coins-assorted-mix-copper.webp",
      "documentId": null,
      "flags": {},
      "_id": "Tl4eHZCu3ls8mx1l",
      "_key": "!tables.results!5SkqTTSbeGviEehL.Tl4eHZCu3ls8mx1l"
    },
    {
      "type": 0,
      "weight": 1,
      "range": [
        76,
        100
      ],
      "drawn": false,
      "documentCollection": "",
      "text": "[[/r 2d6*100]]{Gold}[[/r 2d6*10]]{Platinum}",
      "img": "icons/commodities/currency/coins-assorted-mix-copper.webp",
      "documentId": null,
      "flags": {},
      "_id": "52ujnjFR8eoq4WuW",
      "_key": "!tables.results!5SkqTTSbeGviEehL.52ujnjFR8eoq4WuW"
    },
    {
      "type": 0,
      "weight": 1,
      "range": [
        0,
        0
      ],
      "drawn": false,
      "documentCollection": "",
      "text": "",
      "img": "icons/commodities/currency/coins-assorted-mix-copper.webp",
      "documentId": null,
      "flags": {},
      "_id": "SadwLG9jOLteLvjW",
      "_key": "!tables.results!5SkqTTSbeGviEehL.SadwLG9jOLteLvjW"
    }
  ],
  "formula": "d100",
  "replacement": false,
  "displayRoll": false,
  "folder": null,
  "sort": 0,
  "ownership": {
    "default": 0
  },
  "flags": {},
  "_stats": {
    "systemId": "dnd5e",
    "systemVersion": "2.1.5",
    "coreVersion": "10.291",
    "createdTime": 1688085767682,
    "modifiedTime": 1688085767682,
    "lastModifiedBy": "packsbuilder0000"
  },
  "_id": "5SkqTTSbeGviEehL",
  "_key": "!tables!5SkqTTSbeGviEehL"
}
