{
  "name": "B'rohg Fingernails (sack of 20)",
  "type": "loot",
  "img": "icons/containers/bags/sack-leather-tan.webp",
  "system": {
    "description": {
      "value": "A B'rohg has hard, yellow fingernails. In order to retain their usefulness, the nails must be pulled out slowly and removed whole. Alchemists and healers use the nails to create various concoctions.",
      "chat": "15",
      "unidentified": "Medicine"
    },
    "source": "B'rohg",
    "quantity": 1,
    "weight": 2,
    "price": {
      "value": 100,
      "denomination": "gp"
    },
    "attunement": 0,
    "equipped": false,
    "rarity": "",
    "identified": true
  },
  "effects": [],
  "folder": null,
  "sort": 0,
  "ownership": {
    "default": 0
  },
  "flags": {},
  "_stats": {
    "systemId": "dnd5e",
    "systemVersion": "2.1.5",
    "coreVersion": "10.291",
    "createdTime": 1688174973901,
    "modifiedTime": 1688174973901,
    "lastModifiedBy": "packsbuilder0000"
  },
  "_id": "WmeYfPIlLLWwvzE6",
  "_key": "!items!WmeYfPIlLLWwvzE6"
}
