{
  "name": "Giant Goat Hide",
  "type": "loot",
  "img": "icons/commodities/leather/fur-pelt-off-white.webp",
  "system": {
    "description": {
      "value": "A giant goat is covered in a thick coat fur, often white in color. The coat is primarily used in apparel and bedding.",
      "chat": "10",
      "unidentified": "Nature"
    },
    "source": "Giant Goat",
    "quantity": 1,
    "weight": 5,
    "price": {
      "value": 6,
      "denomination": "gp"
    },
    "attunement": 0,
    "equipped": false,
    "rarity": "",
    "identified": true
  },
  "effects": [],
  "folder": null,
  "sort": 0,
  "ownership": {
    "default": 0
  },
  "flags": {},
  "_stats": {
    "systemId": "dnd5e",
    "systemVersion": "2.1.5",
    "coreVersion": "10.291",
    "createdTime": 1688174975838,
    "modifiedTime": 1688174975838,
    "lastModifiedBy": "packsbuilder0000"
  },
  "_id": "5A8FMczDwW8d2k3c",
  "_key": "!items!5A8FMczDwW8d2k3c"
}
