{
  "name": "Mule Hide",
  "type": "loot",
  "img": "icons/commodities/leather/fur-pelt-off-white.webp",
  "system": {
    "description": {
      "value": "A mule's hide is known for its durability and resistance to moisture absorption. The hide is primarily used to make harnesses, bags, shoes and rugs.",
      "chat": "10",
      "unidentified": "Nature"
    },
    "source": "Mule",
    "quantity": 1,
    "weight": 4,
    "price": {
      "value": 3,
      "denomination": "gp"
    },
    "attunement": 0,
    "equipped": false,
    "rarity": "",
    "identified": true
  },
  "effects": [],
  "folder": null,
  "sort": 0,
  "ownership": {
    "default": 0
  },
  "flags": {},
  "_stats": {
    "systemId": "dnd5e",
    "systemVersion": "2.1.5",
    "coreVersion": "10.291",
    "createdTime": 1688174977200,
    "modifiedTime": 1688174977200,
    "lastModifiedBy": "packsbuilder0000"
  },
  "_id": "gBJXTbYKhjr3U0j7",
  "_key": "!items!gBJXTbYKhjr3U0j7"
}
